{
  "runId": "20260217T231915Z",
  "startedAtUtc": "2026-02-17T23:19:15.5330363Z",
  "finishedAtUtc": "2026-02-17T23:21:57.6324849Z",
  "status": "ok",
  "outputDir": "output/real-estate",
  "publicDataDir": "output/real-estate/public-data",
  "stagingDir": "output/real-estate/staging/public-signals",
  "manualDropDir": "output/real-estate/manual-drops",
  "steps": [
    {
      "name": "fetch_public_data",
      "status": "ok",
      "startedAtUtc": "2026-02-17T23:19:15.5336866Z",
      "durationSec": 39.38,
      "error": ""
    },
    {
      "name": "seed_manual_drops",
      "status": "ok",
      "startedAtUtc": "2026-02-17T23:19:54.9163626Z",
      "durationSec": 0.32,
      "error": ""
    },
    {
      "name": "build_staging",
      "status": "ok",
      "startedAtUtc": "2026-02-17T23:19:55.2410220Z",
      "durationSec": 0.94,
      "error": ""
    },
    {
      "name": "run_recorder_fallback_adapter",
      "status": "ok",
      "startedAtUtc": "2026-02-17T23:19:56.1776766Z",
      "durationSec": 0.33,
      "error": ""
    },
    {
      "name": "run_public_signals",
      "status": "ok",
      "startedAtUtc": "2026-02-17T23:19:56.5106621Z",
      "durationSec": 1.68,
      "error": ""
    },
    {
      "name": "build_macro_context",
      "status": "ok",
      "startedAtUtc": "2026-02-17T23:19:58.1914879Z",
      "durationSec": 0.35,
      "error": ""
    },
    {
      "name": "build_parcel_graph",
      "status": "ok",
      "startedAtUtc": "2026-02-17T23:19:58.5434677Z",
      "durationSec": 0.96,
      "error": ""
    },
    {
      "name": "build_entity_resolution",
      "status": "ok",
      "startedAtUtc": "2026-02-17T23:19:59.5074434Z",
      "durationSec": 0.91,
      "error": ""
    },
    {
      "name": "run_agentic_research",
      "status": "ok",
      "startedAtUtc": "2026-02-17T23:20:00.4153265Z",
      "durationSec": 30.87,
      "error": ""
    },
    {
      "name": "run_opportunity_research",
      "status": "ok",
      "startedAtUtc": "2026-02-17T23:20:31.2860450Z",
      "durationSec": 1.13,
      "error": ""
    },
    {
      "name": "seed_studio_asset_manual_drops",
      "status": "ok",
      "startedAtUtc": "2026-02-17T23:20:32.4172069Z",
      "durationSec": 0.36,
      "error": ""
    },
    {
      "name": "fetch_studio_asset_community_data",
      "status": "ok",
      "startedAtUtc": "2026-02-17T23:20:32.7730513Z",
      "durationSec": 0.4,
      "error": ""
    },
    {
      "name": "run_studio_asset_intelligence",
      "status": "ok",
      "startedAtUtc": "2026-02-17T23:20:33.1780900Z",
      "durationSec": 82.17,
      "error": ""
    },
    {
      "name": "build_needs_context",
      "status": "ok",
      "startedAtUtc": "2026-02-17T23:21:55.3486985Z",
      "durationSec": 0.47,
      "error": ""
    },
    {
      "name": "run_intelligence_analysis",
      "status": "ok",
      "startedAtUtc": "2026-02-17T23:21:55.8144842Z",
      "durationSec": 1.07,
      "error": ""
    },
    {
      "name": "build_review_packet",
      "status": "ok",
      "startedAtUtc": "2026-02-17T23:21:56.8867944Z",
      "durationSec": 0.38,
      "error": ""
    },
    {
      "name": "build_studiobrain_coordinator_adapters",
      "status": "ok",
      "startedAtUtc": "2026-02-17T23:21:57.2720638Z",
      "durationSec": 0.36,
      "error": ""
    }
  ]
}
